setup.py
shinkenplugins/__init__.py
shinkenplugins.plugins.aws_sqs_activity.egg-info/PKG-INFO
shinkenplugins.plugins.aws_sqs_activity.egg-info/SOURCES.txt
shinkenplugins.plugins.aws_sqs_activity.egg-info/dependency_links.txt
shinkenplugins.plugins.aws_sqs_activity.egg-info/entry_points.txt
shinkenplugins.plugins.aws_sqs_activity.egg-info/namespace_packages.txt
shinkenplugins.plugins.aws_sqs_activity.egg-info/requires.txt
shinkenplugins.plugins.aws_sqs_activity.egg-info/top_level.txt
shinkenplugins/plugins/__init__.py
shinkenplugins/plugins/aws_sqs_activity/__init__.py
shinkenplugins/plugins/aws_sqs_activity/aws_sqs_activity.py